exscribe/__init__.py
exscribe/__main__.py
exscribe/cli.py
exscribe/frame_processing.py
exscribe/models.py
exscribe/subtitle.py
exscribe/transcription.py
exscribe/providers/__init__.py
exscribe/providers/base.py
exscribe/providers/gemini.py
exscribe-0.0.1.dist-info/METADATA
exscribe-0.0.1.dist-info/WHEEL
exscribe-0.0.1.dist-info/entry_points.txt
exscribe-0.0.1.dist-info/RECORD
