Metadata-Version: 2.4
Name: exscribe
Version: 0.0.1
Summary: Extract and transcribe subtitles from videos using multimodal models.
Project-URL: homepage, https://github.com/m-krastev/exscribe
Project-URL: issues, https://github.com/m-krastev/exscribe/issues
Author-email: m-krastev <matey.krastev@outlook.com>
License-Expression: MIT
Keywords: LLM,OCR,OpenAI,multimodal,subtitles,transcription,video
Requires-Python: >=3.10
Requires-Dist: av
Requires-Dist: google-genai
Requires-Dist: google-generativeai
Requires-Dist: numpy
Requires-Dist: opencv-python
Requires-Dist: pillow
Requires-Dist: scikit-image
Requires-Dist: tqdm
